electricsystemclasses/ClassConstantLoad.py
electricsystemclasses/ClassEV.py
electricsystemclasses/ClassGen.py
electricsystemclasses/ClassGrid.py
electricsystemclasses/ClassLosses.py
electricsystemclasses/ClassProgrammableLoadActivation.py
electricsystemclasses/ClassStorage.py
electricsystemclasses/ClassVariableLoad.py
electricsystemclasses/__init__.py
electricsystemclasses/prop_calc.py
electricsystemclasses/simulation.py
electricsystemclasses/utils.py
electricsystemclasses-2.3.2.dist-info/LICENSE.txt
electricsystemclasses-2.3.2.dist-info/METADATA
electricsystemclasses-2.3.2.dist-info/WHEEL
electricsystemclasses-2.3.2.dist-info/top_level.txt
electricsystemclasses-2.3.2.dist-info/RECORD
