Metadata-Version: 2.1
Name: electricsystemclasses
Version: 2.3.2
Summary: A collection of electric system components classes for simulation purposes
Author: ropimen
Author-email: rmmenichelli@gmail.com
License: Server Side Public License (SSPL), Version 1.0
Classifier: Programming Language :: Python :: 3
Classifier: License :: Other/Proprietary License
Classifier: Operating System :: OS Independent
Requires-Python: >=3.6
License-File: LICENSE.txt
